linetheme/__init__.py
linetheme/android.py
linetheme/config.py
linetheme/editor.py
linetheme/ios.py
linetheme/theme.py
linetheme-1.0.0.dist-info/LICENSE
linetheme-1.0.0.dist-info/METADATA
linetheme-1.0.0.dist-info/WHEEL
linetheme-1.0.0.dist-info/top_level.txt
linetheme-1.0.0.dist-info/RECORD
